EasyVtk/__init__.py
EasyVtk/commonClasses.py
EasyVtk/commonFunctions.py
EasyVtk/defaults.py
EasyVtk/gmshToVtk.py
EasyVtk/gui.py
EasyVtk/items.py
EasyVtk/objects.py
EasyVtk/properties.py
EasyVtk/colorMaps/ColorMap.py
EasyVtk/colorMaps/__init__.py
EasyVtk-0.9.7.dist-info/METADATA
EasyVtk-0.9.7.dist-info/WHEEL
EasyVtk-0.9.7.dist-info/top_level.txt
EasyVtk-0.9.7.dist-info/RECORD
