Metadata-Version: 2.1
Name: EasyVtk
Version: 0.9.7
Summary: Easy way to create vtk GUI and common objects.
Author: Savvin Anton
Author-email: anv.savvin@gmail.com
License: GPL-3.0 license
Keywords: python
Platform: Windows
Platform: Unix
Classifier: Programming Language :: Python :: 3
